{
  "groups": [
    21213,
    21214,
    21215,
    21216
  ],
  "rooms": {
    "lec": [
      2128,
      402,
      1274,
      304
    ],
    "lab": [
      3212,
      2221,
      4218,
      306
    ],
    "prac": [
      2253,
      3218,
      3120,
      1311,
      2266,
      1156,
      1155,
      4220,
      3317
    ]
  },
  "plan": [
    {
      "teacher": "permyakov",
      "subject": "cybersecurity",
      "subject_type": "lec",
      "groups": [
        21213,
        21214,
        21215,
        21216
      ],
      "times_in_a_week": 1
    },
    {
      "teacher": "nedelko",
      "subject": "machine_learning_methods",
      "subject_type": "lec",
      "groups": [
        21213,
        21214,
        21215,
        21216
      ],
      "times_in_a_week": 1
    },
    {
      "teacher": "nedelko",
      "subject": "machine_learning_methods",
      "subject_type": "prac",
      "groups": [
        21213
      ],
      "times_in_a_week": 1
    },
    {
      "teacher": "vaskevich",
      "subject": "computational_math",
      "subject_type": "lec",
      "groups": [
        21213,
        21214,
        21215,
        21216
      ],
      "times_in_a_week": 1
    },
    {
      "teacher": "vaskevich",
      "subject": "computational_math",
      "subject_type": "prac",
      "groups": [
        21213
      ],
      "times_in_a_week": 1
    },
    {
      "teacher": "patrushev",
      "subject": "data_processing_and_storage",
      "subject_type": "lab",
      "groups": [
        21215
      ],
      "times_in_a_week": 1
    },
    {
      "teacher": "bukshev",
      "subject": "introduction_to_the_mobile_development",
      "subject_type": "lec",
      "groups": [
        21213,
        21214,
        21215,
        21216
      ],
      "times_in_a_week": 1
    },
    {
      "teacher": "miginsky",
      "subject": "data_processing_and_storage",
      "subject_type": "lec",
      "groups": [
        21213,
        21214,
        21215,
        21216
      ],
      "times_in_a_week": 1
    },
    {
      "teacher": "miginsky",
      "subject": "software_engineering",
      "subject_type": "lec",
      "groups": [
        21213,
        21214,
        21215,
        21216
      ],
      "times_in_a_week": 1
    },
    {
      "teacher": "miginsky",
      "subject": "software_engineering",
      "subject_type": "lab",
      "groups": [
        21213
      ],
      "times_in_a_week": 1
    },
    {
      "teacher": "kuzin",
      "subject": "software_engineering",
      "subject_type": "lab",
      "groups": [
        21215
      ],
      "times_in_a_week": 1
    },
    {
      "teacher": "vlasov",
      "subject": "team_work",
      "subject_type": "lec",
      "groups": [
        21213,
        21214,
        21215,
        21216
      ],
      "times_in_a_week": 1
    },
    {
      "teacher": "vlasov",
      "subject": "team_work",
      "subject_type": "prac",
      "groups": [
        21213
      ],
      "times_in_a_week": 1
    },
    {
      "teacher": "balabanov",
      "subject": "cybersecurity",
      "subject_type": "lab",
      "groups": [
        21215,
        21213,
        21214,
        21216
      ],
      "times_in_a_week": 1
    },
    {
      "teacher": "bogdanov",
      "subject": "computational_math",
      "subject_type": "prac",
      "groups": [
        21215
      ],
      "times_in_a_week": 1
    },
    {
      "teacher": "terenteva",
      "subject": "english",
      "subject_type": "prac",
      "groups": [
        21213,
        21215
      ],
      "times_in_a_week": 2
    },
    {
      "teacher": "sitnov",
      "subject": "ctf",
      "subject_type": "lec",
      "groups": [
        21213,
        21215,
        21214,
        21216
      ],
      "times_in_a_week": 2
    },
    {
      "teacher": "zligostev",
      "subject": "data_processing_and_storage",
      "subject_type": "lab",
      "groups": [
        21213
      ],
      "times_in_a_week": 1
    },
    {
      "teacher": "kutalev",
      "subject": "data_processing_and_storage",
      "subject_type": "lab",
      "groups": [
        21214
      ],
      "times_in_a_week": 1
    },
    {
      "teacher": "shvab",
      "subject": "computational_math",
      "subject_type": "prac",
      "groups": [
        21214
      ],
      "times_in_a_week": 1
    },
    {
      "teacher": "golosov",
      "subject": "software_engineering",
      "subject_type": "lab",
      "groups": [
        21214
      ],
      "times_in_a_week": 1
    },
    {
      "teacher": "brek",
      "subject": "software_engineering",
      "subject_type": "lab",
      "groups": [
        21216
      ],
      "times_in_a_week": 1
    },
    {
      "teacher": "plusnin",
      "subject": "data_processing_and_storage",
      "subject_type": "lab",
      "groups": [
        21216
      ],
      "times_in_a_week": 1
    },
    {
      "teacher": "levikin",
      "subject": "computational_math",
      "subject_type": "prac",
      "groups": [
        21216
      ],
      "times_in_a_week": 1
    },
    {
      "teacher": "fizruk",
      "subject": "physical_culture",
      "subject_type": "lec",
      "groups": [
        21213,
        21214,
        21215,
        21216
      ],
      "times_in_a_week": 2
    }
  ],
  "constraints": [
    {
      "name": "teachers_overlapping",
      "args": [
        "permyakov",
        "nedelko"
      ]
    },
    {
      "name": "teachers_overlapping",
      "args": [
        "balabanov",
        "terenteva"
      ]
    },
    {
      "name": "teachers_overlapping",
      "args": [
        "balabanov",
        "sitnov"
      ]
    },
    {
      "name": "teachers_overlapping",
      "args": [
        "terenteva",
        "vaskevich"
      ]
    },
    {
      "name": "number_of_teaching_days",
      "args": [
        {
          "teacher_name": "kuzin",
          "number": 1
        },
        {
          "teacher_name": "bukshev",
          "number": 1
        },
        {
          "teacher_name": "terenteva",
          "number": 1
        },
        {
          "teacher_name": "vaskevich",
          "number": 1
        },
        {
          "teacher_name": "balabanov",
          "number": 1
        }
      ]
    }
  ]
}